Metadata-Version: 2.1
Name: deepNeuroSeg
Version: 0.4
Summary: Deep-learning Tool for White Matter (WM) lesions and Claustrum structure segmentation in brain magnetic resonance imaging (MRI).
Home-page: https://github.com/RitaOlenchuk/deepNeuroSeg
Author: Margaryta Olenchuk
License: MIT
Download-URL: https://github.com/RitaOlenchuk/deepNeuroSeg/archive/refs/tags/v0.4.tar.gz
Keywords: deep-learning,machine-learning,segmentation,MRI,White Matter Lesions,Claustrum
Platform: UNKNOWN
Requires-Python: >=3.9
